functionlayer/__init__.py
functionlayer/__main__.py
functionlayer/cli/__init__.py
functionlayer/cli/main.py
functionlayer/core/__init__.py
functionlayer/core/approval.py
functionlayer/core/types.py
functionlayer/py.typed
functionlayer_ai-0.3.0.dist-info/LICENSE
functionlayer_ai-0.3.0.dist-info/METADATA
functionlayer_ai-0.3.0.dist-info/WHEEL
functionlayer_ai-0.3.0.dist-info/entry_points.txt
functionlayer_ai-0.3.0.dist-info/RECORD
