Metadata-Version: 2.1
Name: functionlayer-ai
Version: 0.3.0
Summary: functionlayer-ai
Home-page: https://github.com/functionlayer/functionlayer
Author: functionlayer authors
Author-email: dexter@metalytics.dev
Requires-Python: >=3.11,<4.0
Classifier: Programming Language :: Python :: 3
Classifier: Programming Language :: Python :: 3.11
Classifier: Programming Language :: Python :: 3.12
Requires-Dist: aiohttp (==3.10.2)
Requires-Dist: human-id (==0.2.0)
Requires-Dist: pydantic (==2.8.2)
Requires-Dist: python-socketio[asyncio-client] (==5.11.3)
Requires-Dist: requests (==2.32.3)
Project-URL: Repository, https://github.com/functionlayer/functionlayer
